{
  "updated_at": "2026-04-06 12:25:46",
  "rows": [
    {
      "type": "us_index",
      "code": "S&P 500",
      "date": "",
      "value": "",
      "prev_value": "",
      "change": "",
      "change_pct": "",
      "market_cap": "",
      "asof_kst": "2026-04-06 12:25:46 | FinanceCharts download (failed)",
      "fetched_at_kst": "2026-04-06 12:25:46"
    },
    {
      "type": "us_index",
      "code": "NASDAQ Composite",
      "date": "",
      "value": "",
      "prev_value": "",
      "change": "",
      "change_pct": "",
      "market_cap": "91.46 T USD",
      "asof_kst": "2026-04-06 12:25:46 | Nasdaq Screener download",
      "fetched_at_kst": "2026-04-06 12:25:46"
    }
  ]
}